.long-description.html
MANIFEST.in
README.txt
setup.py
docs/CHANGES.txt
docs/LICENSE.GPL
docs/LICENSE.txt
p4a/__init__.py
p4a/__init__.pyc
p4a.video.egg-info/PKG-INFO
p4a.video.egg-info/SOURCES.txt
p4a.video.egg-info/dependency_links.txt
p4a.video.egg-info/entry_points.txt
p4a.video.egg-info/namespace_packages.txt
p4a.video.egg-info/not-zip-safe
p4a.video.egg-info/requires.txt
p4a.video.egg-info/top_level.txt
p4a/video/__init__.py
p4a/video/configure.zcml
p4a/video/dimensions.txt
p4a/video/genre.py
p4a/video/interfaces.py
p4a/video/media-player.txt
p4a/video/media.py
p4a/video/metadataextractor.py
p4a/video/migration.py
p4a/video/migration.txt
p4a/video/mimetypes.txt
p4a/video/profiles.zcml
p4a/video/subtype.py
p4a/video/test.zcml
p4a/video/usei18ndude.sh
p4a/video/utils.py
p4a/video/videoanno.py
p4a/video/browser/__init__.py
p4a/video/browser/cd_playlist.xspf.pt
p4a/video/browser/configure.zcml
p4a/video/browser/displays.py
p4a/video/browser/media.py
p4a/video/browser/popup-play.pt
p4a/video/browser/support.py
p4a/video/browser/video-container.pt
p4a/video/browser/video-edit.pt
p4a/video/browser/video-listed-single.pt
p4a/video/browser/video.pt
p4a/video/browser/video.py
p4a/video/browser/video_macros.pt
p4a/video/browser/videocd-popup.pt
p4a/video/browser/widget.py
p4a/video/browser/resources/flowplayer/LICENSE.txt
p4a/video/browser/resources/flowplayer/README.txt
p4a/video/browser/resources/flowplayer/flowplayer-3.2.2.swf
p4a/video/browser/resources/flowplayer/flowplayer.controls-3.2.1.swf
p4a/video/browser/resources/flowplayer/html/flowplayer-3.2.2.min.js
p4a/video/browser/resources/flowplayer/html/index.html
p4a/video/browser/resources/flowplayer/html/play-button-328x240.jpg
p4a/video/browser/resources/flowplayer/html/play.png
p4a/video/browser/resources/flowplayer/html/style.css
p4a/video/browser/resources/vPIP/GenvPIP0-07.html
p4a/video/browser/resources/vPIP/GenvPIP0-07.swf
p4a/video/browser/resources/vPIP/InitSMIL.mov
p4a/video/browser/resources/vPIP/cineViewer-002a.swf
p4a/video/browser/resources/vPIP/close_grey.gif
p4a/video/browser/resources/vPIP/close_hover.gif
p4a/video/browser/resources/vPIP/cortado.jar
p4a/video/browser/resources/vPIP/cvSkins.xml
p4a/video/browser/resources/vPIP/jquery.js
