Metadata-Version: 1.1
Name: p4a.video
Version: 1.4
Summary: Plone4Artists video abstraction library
Home-page: http://plone.org/products/plone4artistsvideo
Author: Rocky Burt
Author-email: rocky@serverzen.com
License: GPL
Keywords: Plone4Artists video multimedia quicktime flash flv vodcast
Platform: UNKNOWN
Classifier: Framework :: Zope2
Classifier: Framework :: Zope3
Classifier: Framework :: Plone
Classifier: Programming Language :: Python
Classifier: License :: OSI Approved :: GNU General Public License (GPL)
Classifier: Topic :: Software Development :: Libraries :: Python Modules
Classifier: Topic :: Multimedia :: Video
